flowsaber/__init__.py
flowsaber/api.py
flowsaber/cli.py
flowsaber/client/__init__.py
flowsaber/client/agent.py
flowsaber/client/client.py
flowsaber/core/__init__.py
flowsaber/core/base.py
flowsaber/core/channel.py
flowsaber/core/context.py
flowsaber/core/default_context.py
flowsaber/core/flow.py
flowsaber/core/operators.py
flowsaber/core/task.py
flowsaber/core/utils.py
flowsaber/core/engine/__init__.py
flowsaber/core/engine/flow_runner.py
flowsaber/core/engine/runner.py
flowsaber/core/engine/scheduler.py
flowsaber/core/engine/task_runner.py
flowsaber/core/utility/__init__.py
flowsaber/core/utility/cache.py
flowsaber/core/utility/executor.py
flowsaber/core/utility/state.py
flowsaber/core/utility/target.py
flowsaber/server/__init__.py
flowsaber/server/app/__init__.py
flowsaber/server/app/app.py
flowsaber/server/app/resolvers.py
flowsaber/server/app/graphql_schema/agent.graphql
flowsaber/server/app/graphql_schema/flow.graphql
flowsaber/server/app/graphql_schema/log.graphql
flowsaber/server/app/graphql_schema/run.graphql
flowsaber/server/app/graphql_schema/schema.graphql
flowsaber/server/app/graphql_schema/state.graphql
flowsaber/server/app/graphql_schema/types.graphql
flowsaber/server/database/__init__.py
flowsaber/server/database/db.py
flowsaber/server/database/models.py
flowsaber/tasks/__init__.py
flowsaber/tasks/aws.py
flowsaber/tasks/email.py
flowsaber/tasks/shell.py
flowsaber/tasks/bio/__init__.py
flowsaber/tasks/bio/fetch_igenome.py
flowsaber/tasks/bio/fetch_refgenie.py
flowsaber/utility/__init__.py
flowsaber/utility/aws.py
flowsaber/utility/context.py
flowsaber/utility/logging.py
flowsaber/utility/statutils.py
flowsaber/utility/utils.py
flowsaber-0.1.3.7.0.data/scripts/flowsaber
flowsaber-0.1.3.7.0.dist-info/LICENSE
flowsaber-0.1.3.7.0.dist-info/METADATA
flowsaber-0.1.3.7.0.dist-info/WHEEL
flowsaber-0.1.3.7.0.dist-info/top_level.txt
flowsaber-0.1.3.7.0.dist-info/RECORD
