Metadata-Version: 2.1
Name: flowsaber
Version: 0.1.3.7.0
Summary: A dataflow based workflow framework
Home-page: https://github.com/zhqu1148980644/flowsaber
Author: bakezq
Author-email: zhongquan789@gmail.com
License: MIT
Keywords: dataflow,workflow,asyncio
Platform: UNKNOWN
Classifier: Development Status :: 3 - Alpha
Classifier: Operating System :: POSIX
Classifier: Programming Language :: Python
Classifier: Programming Language :: Python :: 3
Classifier: Programming Language :: Python :: 3.7
Classifier: Programming Language :: Python :: 3.8
Classifier: Programming Language :: Python :: 3.9
Classifier: License :: OSI Approved :: MIT License
Classifier: Intended Audience :: Science/Research
Classifier: Topic :: Scientific/Engineering :: Bio-Informatics
Classifier: Topic :: Software Development :: Libraries
Requires-Python: >=3.7, <4
Requires-Dist: makefun
Requires-Dist: cloudpickle
Requires-Dist: dask
Requires-Dist: distributed
Requires-Dist: psutil
Requires-Dist: aiohttp
Requires-Dist: pydantic
Requires-Dist: fire
Requires-Dist: ariadne
Requires-Dist: uvicorn
Requires-Dist: dnspython
Requires-Dist: motor
Provides-Extra: bio
Requires-Dist: botocore ; extra == 'bio'
Provides-Extra: test
Requires-Dist: pytest ; extra == 'test'
Requires-Dist: pytest-cov ; extra == 'test'
Requires-Dist: httpimport ; extra == 'test'
Requires-Dist: autodocsumm ; extra == 'test'
Requires-Dist: pysam ; extra == 'test'
Requires-Dist: matplotlib ; extra == 'test'
